LICENSE.txt
MANIFEST.in
README
requirements.txt
setup.py
test-requirements.txt
turbolift/__init__.py
turbolift/executable.py
turbolift/info.py
turbolift/worker.py
turbolift.egg-info/PKG-INFO
turbolift.egg-info/SOURCES.txt
turbolift.egg-info/dependency_links.txt
turbolift.egg-info/entry_points.txt
turbolift.egg-info/requires.txt
turbolift.egg-info/top_level.txt
turbolift/arguments/__init__.py
turbolift/arguments/archive.py
turbolift/arguments/authgroup.py
turbolift/arguments/clone.py
turbolift/arguments/command.py
turbolift/arguments/delete.py
turbolift/arguments/download.py
turbolift/arguments/headers.py
turbolift/arguments/optionals.py
turbolift/arguments/tsync.py
turbolift/arguments/upload.py
turbolift/authentication/__init__.py
turbolift/authentication/authentication.py
turbolift/clouderator/__init__.py
turbolift/clouderator/actions.py
turbolift/logger/__init__.py
turbolift/logger/logger.py
turbolift/methods/__init__.py
turbolift/methods/archive.py
turbolift/methods/cdn_command.py
turbolift/methods/clone.py
turbolift/methods/delete.py
turbolift/methods/download.py
turbolift/methods/list.py
turbolift/methods/show.py
turbolift/methods/update.py
turbolift/methods/upload.py
turbolift/utils/__init__.py
turbolift/utils/auth_utils.py
turbolift/utils/basic_utils.py
turbolift/utils/http_utils.py
turbolift/utils/multi_utils.py
turbolift/utils/report_utils.py