Metadata-Version: 1.1
Name: turbolift
Version: 2.1.0
Summary: OpenStack Swift -Cloud Files- Uploader
Home-page: https://github.com/cloudnull/turbolift.git
Author: Kevin Carter
Author-email: kevin@cloudnull.com
License: GNU General Public License v3 or later (GPLv3+)
Platform: UNKNOWN
Classifier: Development Status :: 5 - Production/Stable
Classifier: Intended Audience :: Information Technology
Classifier: Intended Audience :: System Administrators
Classifier: Intended Audience :: Developers
Classifier: Operating System :: OS Independent
Classifier: License :: OSI Approved :: GNU General Public License v3 or later (GPLv3+)
Classifier: Programming Language :: Python :: 2.6
Classifier: Programming Language :: Python :: 2.7
Classifier: Topic :: Utilities
Classifier: Topic :: Software Development :: Libraries :: Python Modules
